<annotation>
	<folder>images</folder>
	<filename>bottle_013.jpg</filename>
	<path>C:\Users\bglim\git\PDI-Project\db\training007\emptybottle\augmented\images\bottle_013.jpg</path>
	<source>
		<database>Unknown</database>
	</source>
	<size>
		<width>300</width>
		<height>300</height>
		<depth>3</depth>
	</size>
	<segmented>0</segmented>
	<object>
		<name>emptybottle</name>
		<pose>Unspecified</pose>
		<truncated>0</truncated>
		<difficult>1</difficult>
		<bndbox>
			<xmin>100</xmin>
			<ymin>14</ymin>
			<xmax>199</xmax>
			<ymax>285</ymax>
		</bndbox>
	</object>
</annotation>