<annotation>
	<folder>tire</folder>
	<filename>tire_99.jpg</filename>
	<path>C:\Users\Bruno\git\pdi-project\db\tire\tire_99.jpg</path>
	<source>
		<database>Unknown</database>
	</source>
	<size>
		<width>275</width>
		<height>183</height>
		<depth>3</depth>
	</size>
	<segmented>0</segmented>
	<object>
		<name>tire</name>
		<pose>Unspecified</pose>
		<truncated>1</truncated>
		<difficult>0</difficult>
		<bndbox>
			<xmin>1</xmin>
			<ymin>145</ymin>
			<xmax>58</xmax>
			<ymax>169</ymax>
		</bndbox>
	</object>
	<object>
		<name>tire</name>
		<pose>Unspecified</pose>
		<truncated>0</truncated>
		<difficult>0</difficult>
		<bndbox>
			<xmin>30</xmin>
			<ymin>128</ymin>
			<xmax>78</xmax>
			<ymax>164</ymax>
		</bndbox>
	</object>
	<object>
		<name>tire</name>
		<pose>Unspecified</pose>
		<truncated>0</truncated>
		<difficult>0</difficult>
		<bndbox>
			<xmin>53</xmin>
			<ymin>115</ymin>
			<xmax>95</xmax>
			<ymax>151</ymax>
		</bndbox>
	</object>
	<object>
		<name>tire</name>
		<pose>Unspecified</pose>
		<truncated>0</truncated>
		<difficult>0</difficult>
		<bndbox>
			<xmin>29</xmin>
			<ymin>102</ymin>
			<xmax>70</xmax>
			<ymax>128</ymax>
		</bndbox>
	</object>
	<object>
		<name>tire</name>
		<pose>Unspecified</pose>
		<truncated>0</truncated>
		<difficult>0</difficult>
		<bndbox>
			<xmin>50</xmin>
			<ymin>76</ymin>
			<xmax>92</xmax>
			<ymax>106</ymax>
		</bndbox>
	</object>
	<object>
		<name>tire</name>
		<pose>Unspecified</pose>
		<truncated>0</truncated>
		<difficult>0</difficult>
		<bndbox>
			<xmin>81</xmin>
			<ymin>65</ymin>
			<xmax>127</xmax>
			<ymax>116</ymax>
		</bndbox>
	</object>
	<object>
		<name>tire</name>
		<pose>Unspecified</pose>
		<truncated>0</truncated>
		<difficult>0</difficult>
		<bndbox>
			<xmin>105</xmin>
			<ymin>120</ymin>
			<xmax>148</xmax>
			<ymax>143</ymax>
		</bndbox>
	</object>
	<object>
		<name>tire</name>
		<pose>Unspecified</pose>
		<truncated>0</truncated>
		<difficult>0</difficult>
		<bndbox>
			<xmin>19</xmin>
			<ymin>90</ymin>
			<xmax>49</xmax>
			<ymax>129</ymax>
		</bndbox>
	</object>
	<object>
		<name>tire</name>
		<pose>Unspecified</pose>
		<truncated>0</truncated>
		<difficult>0</difficult>
		<bndbox>
			<xmin>110</xmin>
			<ymin>106</ymin>
			<xmax>149</xmax>
			<ymax>127</ymax>
		</bndbox>
	</object>
</annotation>
