<annotation>
	<folder>images</folder>
	<filename>flowerpot_059.jpg</filename>
	<path>C:\Users\Bruno\git\pdi-project\db\training003\flower_pot\images\flowerpot_059.jpg</path>
	<source>
		<database>Unknown</database>
	</source>
	<size>
		<width>736</width>
		<height>736</height>
		<depth>3</depth>
	</size>
	<segmented>0</segmented>
	<object>
		<name>flowerpot</name>
		<pose>Unspecified</pose>
		<truncated>0</truncated>
		<difficult>0</difficult>
		<bndbox>
			<xmin>3</xmin>
			<ymin>620</ymin>
			<xmax>108</xmax>
			<ymax>726</ymax>
		</bndbox>
	</object>
	<object>
		<name>flowerpot</name>
		<pose>Unspecified</pose>
		<truncated>0</truncated>
		<difficult>0</difficult>
		<bndbox>
			<xmin>147</xmin>
			<ymin>620</ymin>
			<xmax>262</xmax>
			<ymax>724</ymax>
		</bndbox>
	</object>
	<object>
		<name>flowerpot</name>
		<pose>Unspecified</pose>
		<truncated>0</truncated>
		<difficult>0</difficult>
		<bndbox>
			<xmin>263</xmin>
			<ymin>551</ymin>
			<xmax>430</xmax>
			<ymax>721</ymax>
		</bndbox>
	</object>
	<object>
		<name>flowerpot</name>
		<pose>Unspecified</pose>
		<truncated>0</truncated>
		<difficult>0</difficult>
		<bndbox>
			<xmin>482</xmin>
			<ymin>557</ymin>
			<xmax>585</xmax>
			<ymax>657</ymax>
		</bndbox>
	</object>
	<object>
		<name>flowerpot</name>
		<pose>Unspecified</pose>
		<truncated>1</truncated>
		<difficult>0</difficult>
		<bndbox>
			<xmin>595</xmin>
			<ymin>548</ymin>
			<xmax>736</xmax>
			<ymax>718</ymax>
		</bndbox>
	</object>
	<object>
		<name>flowerpot</name>
		<pose>Unspecified</pose>
		<truncated>0</truncated>
		<difficult>0</difficult>
		<bndbox>
			<xmin>454</xmin>
			<ymin>390</ymin>
			<xmax>550</xmax>
			<ymax>469</ymax>
		</bndbox>
	</object>
	<object>
		<name>flowerpot</name>
		<pose>Unspecified</pose>
		<truncated>0</truncated>
		<difficult>0</difficult>
		<bndbox>
			<xmin>327</xmin>
			<ymin>390</ymin>
			<xmax>418</xmax>
			<ymax>467</ymax>
		</bndbox>
	</object>
	<object>
		<name>flowerpot</name>
		<pose>Unspecified</pose>
		<truncated>0</truncated>
		<difficult>0</difficult>
		<bndbox>
			<xmin>408</xmin>
			<ymin>209</ymin>
			<xmax>491</xmax>
			<ymax>281</ymax>
		</bndbox>
	</object>
	<object>
		<name>flowerpot</name>
		<pose>Unspecified</pose>
		<truncated>0</truncated>
		<difficult>0</difficult>
		<bndbox>
			<xmin>484</xmin>
			<ymin>151</ymin>
			<xmax>615</xmax>
			<ymax>279</ymax>
		</bndbox>
	</object>
	<object>
		<name>flowerpot</name>
		<pose>Unspecified</pose>
		<truncated>0</truncated>
		<difficult>0</difficult>
		<bndbox>
			<xmin>223</xmin>
			<ymin>345</ymin>
			<xmax>339</xmax>
			<ymax>468</ymax>
		</bndbox>
	</object>
	<object>
		<name>flowerpot</name>
		<pose>Unspecified</pose>
		<truncated>0</truncated>
		<difficult>0</difficult>
		<bndbox>
			<xmin>144</xmin>
			<ymin>472</ymin>
			<xmax>239</xmax>
			<ymax>555</ymax>
		</bndbox>
	</object>
	<object>
		<name>flowerpot</name>
		<pose>Unspecified</pose>
		<truncated>0</truncated>
		<difficult>0</difficult>
		<bndbox>
			<xmin>26</xmin>
			<ymin>412</ymin>
			<xmax>165</xmax>
			<ymax>550</ymax>
		</bndbox>
	</object>
</annotation>
