<annotation>
	<folder>images</folder>
	<filename>bottle_141.jpg</filename>
	<path>C:\Users\Bruno\git\pdi-project\db\training003\empty_bottle\images\bottle_141.jpg</path>
	<source>
		<database>Unknown</database>
	</source>
	<size>
		<width>500</width>
		<height>375</height>
		<depth>1</depth>
	</size>
	<segmented>0</segmented>
	<object>
		<name>emptybottle</name>
		<pose>Unspecified</pose>
		<truncated>0</truncated>
		<difficult>0</difficult>
		<bndbox>
			<xmin>68</xmin>
			<ymin>108</ymin>
			<xmax>142</xmax>
			<ymax>339</ymax>
		</bndbox>
	</object>
	<object>
		<name>emptybottle</name>
		<pose>Unspecified</pose>
		<truncated>0</truncated>
		<difficult>0</difficult>
		<bndbox>
			<xmin>131</xmin>
			<ymin>94</ymin>
			<xmax>198</xmax>
			<ymax>363</ymax>
		</bndbox>
	</object>
	<object>
		<name>emptybottle</name>
		<pose>Unspecified</pose>
		<truncated>0</truncated>
		<difficult>0</difficult>
		<bndbox>
			<xmin>236</xmin>
			<ymin>96</ymin>
			<xmax>304</xmax>
			<ymax>361</ymax>
		</bndbox>
	</object>
	<object>
		<name>emptybottle</name>
		<pose>Unspecified</pose>
		<truncated>0</truncated>
		<difficult>0</difficult>
		<bndbox>
			<xmin>373</xmin>
			<ymin>94</ymin>
			<xmax>440</xmax>
			<ymax>341</ymax>
		</bndbox>
	</object>
	<object>
		<name>emptybottle</name>
		<pose>Unspecified</pose>
		<truncated>0</truncated>
		<difficult>0</difficult>
		<bndbox>
			<xmin>303</xmin>
			<ymin>20</ymin>
			<xmax>375</xmax>
			<ymax>337</ymax>
		</bndbox>
	</object>
	<object>
		<name>emptybottle</name>
		<pose>Unspecified</pose>
		<truncated>0</truncated>
		<difficult>0</difficult>
		<bndbox>
			<xmin>178</xmin>
			<ymin>38</ymin>
			<xmax>257</xmax>
			<ymax>338</ymax>
		</bndbox>
	</object>
</annotation>
